tuik_scraper/__init__.py
tuik_scraper/scraper.py
tuik_scraper-1.0.1.dist-info/METADATA
tuik_scraper-1.0.1.dist-info/WHEEL
tuik_scraper-1.0.1.dist-info/top_level.txt
tuik_scraper-1.0.1.dist-info/RECORD
