Metadata-Version: 2.1
Name: tuik_scraper
Version: 1.0.1
Summary: TÜİK veri çekme ve indirme kütüphanesi
Home-page: https://github.com/kaboya19/tuik_scraper
Author: Bora Kaya
Author-email: bora.587@hotmail.com
Classifier: Programming Language :: Python :: 3
Classifier: License :: OSI Approved :: MIT License
Classifier: Operating System :: OS Independent
Requires-Python: >=3.6
Requires-Dist: requests
Requires-Dist: pandas
Requires-Dist: beautifulsoup4
Requires-Dist: selenium
Requires-Dist: webdriver-manager
